selfsearch/__init__.py
selfsearch-0.1.0.dist-info/LICENSE
selfsearch-0.1.0.dist-info/METADATA
selfsearch-0.1.0.dist-info/WHEEL
selfsearch-0.1.0.dist-info/RECORD
