Metadata-Version: 2.3
Name: selfsearch
Version: 0.1.0
Summary: First step in AI alignment
License: Apache 2.0
Author: AndrewMpapalika
Requires-Python: >=3.9
Classifier: License :: Other/Proprietary License
Classifier: Programming Language :: Python :: 3
Classifier: Programming Language :: Python :: 3.9
Classifier: Programming Language :: Python :: 3.10
Classifier: Programming Language :: Python :: 3.11
Classifier: Programming Language :: Python :: 3.12
Classifier: Programming Language :: Python :: 3.13
